csvdatautils/__init__.py
csvdatautils/csvdata.py
csvdatautils/csvdatarow.py
csvdatautils-0.0.1.dist-info/METADATA
csvdatautils-0.0.1.dist-info/WHEEL
csvdatautils-0.0.1.dist-info/top_level.txt
csvdatautils-0.0.1.dist-info/RECORD
