Metadata-Version: 2.1
Name: csvdatautils
Version: 0.0.1
Summary: A Python Package containing simple utilities for parsing and using CSV, or CSV like, files.
Home-page: https://github.com/jmount1992/csvdatautils-python
Author: James Mount
Author-email: jmount1992@gmail.com
Classifier: Development Status :: 4 - Beta
Classifier: Programming Language :: Python :: 3
Classifier: License :: OSI Approved :: MIT License
Classifier: Operating System :: OS Independent
